altastata/__init__.py
altastata/altastata_functions.py
altastata/altastata_pytorch_dataset.py
altastata/altastata_tensorflow_dataset.py
altastata/base_gateway.py
altastata/fsspec.py
altastata/lib/altastata-hadoop-all.jar
altastata/lib/bcpkix-jdk18on-1.80.jar
altastata/lib/bcprov-jdk18on-1.80.jar
altastata/lib/bcutil-jdk18on-1.80.jar
altastata/lib/py4j0.10.9.5.jar
altastata-0.1.21.dist-info/METADATA
altastata-0.1.21.dist-info/WHEEL
altastata-0.1.21.dist-info/top_level.txt
altastata-0.1.21.dist-info/RECORD
