Metadata-Version: 2.4
Name: altastata
Version: 0.1.21
Summary: A Python package for Altastata data processing and machine learning integration
Home-page: https://github.com/sergevil/altastata-python-package
Author: Serge Vilvovsky
Author-email: serge.vilvovsky@altastata.com
Classifier: Programming Language :: Python :: 3
Classifier: License :: OSI Approved :: MIT License
Classifier: Operating System :: OS Independent
Requires-Python: >=3.8
Requires-Dist: py4j==0.10.9.5
Requires-Dist: fsspec>=2023.1.0
Dynamic: author
Dynamic: author-email
Dynamic: classifier
Dynamic: description
Dynamic: description-content-type
Dynamic: home-page
Dynamic: requires-dist
Dynamic: requires-python
Dynamic: summary
